bbrl/__init__.py
bbrl/_version.py
bbrl/stats.py
bbrl/test_transition.py
bbrl/workspace.py
bbrl/agents/README.md
bbrl/agents/__init__.py
bbrl/agents/agent.py
bbrl/agents/asynchronous.py
bbrl/agents/dataloader.py
bbrl/agents/gymnasium.py
bbrl/agents/remote.py
bbrl/agents/seeding.py
bbrl/agents/utils.py
bbrl/utils/__init__.py
bbrl/utils/chrono.py
bbrl/utils/distributions.py
bbrl/utils/functional.py
bbrl/utils/logger.py
bbrl/utils/replay_buffer.py
bbrl/utils/utils.py
bbrl/utils/gymnasium/__init__.py
bbrl/utils/gymnasium/distributions.py
bbrl/visu/__init__.py
bbrl/visu/common.py
bbrl/visu/play.py
bbrl/visu/plot_critics.py
bbrl/visu/plot_policies.py
bbrl/visu/plot_trajectories.py
bbrl/visu/svpg_histograms.py
bbrl-1.0.1.dist-info/licenses/LICENSE
bbrl-1.0.1.dist-info/METADATA
bbrl-1.0.1.dist-info/WHEEL
bbrl-1.0.1.dist-info/top_level.txt
bbrl-1.0.1.dist-info/RECORD
