Metadata-Version: 2.4
Name: bbrl
Version: 1.0.1
Summary: RL library inspired from salina
Author-email: Olivier Sigaud <Olivier.Sigaud@isir.upmc.fr>
License: MIT
Project-URL: repository, https://github.com/osigaud/bbrl.git
License-File: LICENSE
Requires-Dist: torch>=1.9.0
Requires-Dist: torchvision
Requires-Dist: tensorboard
Requires-Dist: tqdm
Requires-Dist: hydra-core
Requires-Dist: numpy
Requires-Dist: pandas
Requires-Dist: opencv-python
Requires-Dist: omegaconf
Requires-Dist: matplotlib
Requires-Dist: seaborn
Requires-Dist: scipy
Requires-Dist: bootstrapped
Requires-Dist: gymnasium>1
Requires-Dist: moviepy
Dynamic: license-file
